postie/__init__.py
postie/admin.py
postie/apps.py
postie/backends.py
postie/const.py
postie/entities.py
postie/forms.py
postie/models.py
postie/querysets.py
postie/shortcuts.py
postie/tasks.py
postie/utils.py
postie/integrations/__init__.py
postie/integrations/tilda/__init__.py
postie/integrations/tilda/admin.py
postie/integrations/tilda/apps.py
postie/integrations/tilda/hook.py
postie/integrations/tilda/models.py
postie/integrations/tilda/services.py
postie/integrations/tilda/tasks.py
postie/integrations/tilda/urls.py
postie/integrations/tilda/utils.py
postie/integrations/tilda/migrations/0001_initial.py
postie/integrations/tilda/migrations/0002_preferences_project_id.py
postie/integrations/tilda/migrations/__init__.py
postie/locale/en/LC_MESSAGES/django.mo
postie/locale/en/LC_MESSAGES/django.po
postie/locale/ru/LC_MESSAGES/django.mo
postie/locale/ru/LC_MESSAGES/django.po
postie/locale/uk/LC_MESSAGES/django.mo
postie/locale/uk/LC_MESSAGES/django.po
postie/management/__init__.py
postie/management/commands/__init__.py
postie/management/commands/create_templates.py
postie/migrations/0001_initial.py
postie/migrations/0002_auto_20180501_0834.py
postie/migrations/0003_auto_20180504_0340.py
postie/migrations/0004_auto_20200323_1754.py
postie/migrations/0005_auto_20200704_1647.py
postie/migrations/__init__.py
postie/tests/__init__.py
postie/tests/settings.py
postie/tests/test_backends.py
postie/tests/test_commands.py
postie/tests/test_entities.py
postie/tests/test_forms.py
postie/tests/test_letters.py
postie/tests/test_mail.py
postie/tests/test_models.py
postie/tests/test_shortcuts.py
postie/tests/test_tasks.py
postie/tests/test_tilda.py
postie/tests/test_utils.py
postie/tests/urls.py
django_postie-0.8.1.dist-info/LICENSE
django_postie-0.8.1.dist-info/METADATA
django_postie-0.8.1.dist-info/WHEEL
django_postie-0.8.1.dist-info/top_level.txt
django_postie-0.8.1.dist-info/RECORD
