Metadata-Version: 2.1
Name: django-postie
Version: 0.8.1
Summary: Django mailing through admin
Home-page: https://gitlab.com/cyberbudy/django-postie
Author: cyberbudy
Author-email: cyberbudy@gmail.com
License: MIT
Platform: UNKNOWN
Classifier: Environment :: Web Environment
Classifier: Framework :: Django
Classifier: Intended Audience :: Developers
Classifier: Programming Language :: Python :: 3
Requires-Python: >3.7.0
Requires-Dist: django (>=2)
Requires-Dist: django-ckeditor
Requires-Dist: django-codemirror2
Requires-Dist: django-model-utils
Requires-Dist: django-parler
Requires-Dist: django-solo
Requires-Dist: tilda-wrapper-api
